PhyloTreeClustering/PhyloTreeClustering.py
PhyloTreeClustering/__init__.py
PhyloTreeClustering/calculate_pdm.py
PhyloTreeClustering/calinski_harabasz.py
PhyloTreeClustering/medicc_functions.py
phylotreeclus-1.0.1.data/scripts/phylotreeclus
phylotreeclus-1.0.1.dist-info/METADATA
phylotreeclus-1.0.1.dist-info/WHEEL
phylotreeclus-1.0.1.dist-info/top_level.txt
phylotreeclus-1.0.1.dist-info/RECORD
