Metadata-Version: 2.1
Name: phylotreeclus
Version: 1.0.1
Summary: Clustering algorithm for phylogenetic cancer evolution trees
Home-page: https://bitbucket.org/schwarzlab/phylotreeclustering
Author: Elisa Billard
Author-email: elisabillard1905@gmail.com
Classifier: Programming Language :: Python :: 3
Classifier: License :: OSI Approved :: MIT License
Classifier: Operating System :: OS Independent
Requires-Dist: numpy (>=1.20.1)
Requires-Dist: pandas (>=1.2.2)
Requires-Dist: biopython (>=1.78)
Requires-Dist: matplotlib (>=3.3.4)
Requires-Dist: scikit-learn (>=1.2.2)
